{"chores":[{"id":1,"name":"Polish silverware","description":"Inside trophy cabinet","userId":1,"createdAt":"2020-10-05T14:41:28.251+00:00"},{"id":2,"name":"Loaded dishwasher","description":"","userId":1,"createdAt":"2020-10-06T15:41:28.251+00:00"},{"id":3,"name":"Made bed","description":"Fresh sheets","userId":1,"createdAt":"2020-10-10T14:41:28.251+00:00"},{"id":4,"name":"Vacuumed","description":"Living room","userId":2,"createdAt":"2020-10-05T10:30:28.251+00:00"},{"id":5,"name":"Emptied recycling","description":"","userId":1,"createdAt":"2020-10-12T14:41:28.251+00:00"},{"id":6,"name":"Dusting","description":"","userId":2,"createdAt":"2020-10-20T14:41:28.251+00:00"}],"users":[{"id":1,"name":"Nick Baumer"},{"id":2,"name":"John Smith"},{"id":3,"name":"Amy Anderson"}]}